ytpipe/__init__.py
ytpipe/batch_processing.py
ytpipe/cli.py
ytpipe/config.py
ytpipe/download.py
ytpipe/transcribe.py
ytpipe/__pycache__/__init__.cpython-313.pyc
ytpipe/__pycache__/batch_processing.cpython-313.pyc
ytpipe/__pycache__/cli.cpython-313.pyc
ytpipe/__pycache__/config.cpython-313.pyc
ytpipe/__pycache__/download.cpython-313.pyc
ytpipe/__pycache__/transcribe.cpython-313.pyc
ytpipe-0.1.7.dist-info/METADATA
ytpipe-0.1.7.dist-info/WHEEL
ytpipe-0.1.7.dist-info/entry_points.txt
ytpipe-0.1.7.dist-info/top_level.txt
ytpipe-0.1.7.dist-info/RECORD
