Metadata-Version: 2.4
Name: ytpipe
Version: 0.1.7
Summary: YouTube audio download and faster-whisper transcription pipeline.
Author-email: Adnan Mehremic <mehremic.a@gmail.com>
License: MIT
Keywords: youtube,audio,transcription,whisper,faster-whisper,yt-dlp
Classifier: Programming Language :: Python :: 3
Classifier: Programming Language :: Python :: 3.10
Classifier: Programming Language :: Python :: 3.11
Classifier: Programming Language :: Python :: 3.12
Classifier: License :: OSI Approved :: MIT License
Classifier: Operating System :: OS Independent
Requires-Python: >=3.10
Requires-Dist: yt-dlp[default]>=2025.11.12
Requires-Dist: faster-whisper<2.0.0,>=1.0.0
Requires-Dist: tqdm>=4.66.0
Requires-Dist: typer>=0.12.0
Provides-Extra: dev
Requires-Dist: pytest>=8.0.0; extra == "dev"
Requires-Dist: mypy>=1.10.0; extra == "dev"
Requires-Dist: black>=24.0.0; extra == "dev"
Requires-Dist: ruff>=0.5.0; extra == "dev"
Requires-Dist: twine>=5.0.0; extra == "dev"
Requires-Dist: build>=1.2.0; extra == "dev"
Provides-Extra: full
Requires-Dist: static-ffmpeg>=2.5; extra == "full"
Provides-Extra: gpu
Requires-Dist: nvidia-cudnn-cu12>=9.0.0; extra == "gpu"
Requires-Dist: nvidia-cublas-cu12>=12.0.0; extra == "gpu"
